pygus/__init__.py
pygus/gus/__init__.py
pygus/gus/agents.py
pygus/gus/allometrics.py
pygus/gus/enums.py
pygus/gus/inputs/adam_bbox.csv
pygus/gus/inputs/allometrics.json
pygus/gus/inputs/amsterdam_all_trees_1000.csv
pygus/gus/inputs/amsterdam_trees.csv
pygus/gus/inputs/hotfix_ids.ipynb
pygus/gus/inputs/scenario.json
pygus/gus/inputs/site.json
pygus/gus/inputs/trees.csv
pygus/gus/models/__init__.py
pygus/gus/models/config.py
pygus/gus/models/urban.py
pygus/gus/outputs/trees_yearly.json
pygus/gus/population.py
pygus/gus/utilities.py
pygus/gus/weather.py
pygus/impacts/__init__.py
pygus/impacts/carbon.py
pygus/impacts/water.py
pygus-2.2.1.dist-info/LICENSE
pygus-2.2.1.dist-info/METADATA
pygus-2.2.1.dist-info/WHEEL
pygus-2.2.1.dist-info/RECORD
