Metadata-Version: 2.1
Name: pyGUS
Version: 2.2.1
Summary: Green Unified Scenarios - A digital twin representation, simulation of urban forests and their impact analysis.
Home-page: https://github.com/lucidmindsai/gus
License: Apache-2.0
Author: Bulent Ozel
Author-email: bulent@lucidminds.ai
Maintainer: Oguzhan Yayla
Maintainer-email: oguzhan@lucidminds.ai
Requires-Python: >=3.10,<3.13
Classifier: Development Status :: 4 - Beta
Classifier: Environment :: Console
Classifier: Intended Audience :: Developers
Classifier: License :: OSI Approved :: Apache Software License
Classifier: License :: Other/Proprietary License
Classifier: Operating System :: OS Independent
Classifier: Programming Language :: Python
Classifier: Programming Language :: Python :: 3
Classifier: Programming Language :: Python :: 3.10
Classifier: Programming Language :: Python :: 3.11
Classifier: Programming Language :: Python :: 3.12
Classifier: Programming Language :: Python :: 3 :: Only
Classifier: Topic :: Software Development :: Libraries
Classifier: Topic :: Software Development :: Libraries :: Python Modules
Classifier: Topic :: Utilities
Requires-Dist: fuzzywuzzy (>=0.18.0,<0.19.0)
Requires-Dist: mesa (>=0.8.9,<0.9.0)
Requires-Dist: pandas (>=1.3.3,<2.0.0)
Requires-Dist: python-levenshtein (>=0.21.1,<0.22.0)
Requires-Dist: shapely (>=2.0.3,<3.0.0)
Requires-Dist: termcolor (>=2.1.1,<3.0.0)
Requires-Dist: utm (>=0.7.0,<0.8.0)
Project-URL: Repository, https://github.com/lucidmindsai/gus
